thonny_circuitpython-0.2b2.dist-info/METADATA
thonny_circuitpython-0.2b2.dist-info/RECORD
thonny_circuitpython-0.2b2.dist-info/WHEEL
thonny_circuitpython-0.2b2.dist-info/top_level.txt
thonnycontrib/circuitpython/__init__.py
thonnycontrib/circuitpython/api_stubs/analogio.py
thonnycontrib/circuitpython/api_stubs/array.py
thonnycontrib/circuitpython/api_stubs/audiobusio.py
thonnycontrib/circuitpython/api_stubs/audioio.py
thonnycontrib/circuitpython/api_stubs/bitbangio.py
thonnycontrib/circuitpython/api_stubs/board.py
thonnycontrib/circuitpython/api_stubs/builtins.py
thonnycontrib/circuitpython/api_stubs/busio.py
thonnycontrib/circuitpython/api_stubs/digitalio.py
thonnycontrib/circuitpython/api_stubs/framebuf.py
thonnycontrib/circuitpython/api_stubs/gamepad.py
thonnycontrib/circuitpython/api_stubs/gc.py
thonnycontrib/circuitpython/api_stubs/math.py
thonnycontrib/circuitpython/api_stubs/microcontroller.py
thonnycontrib/circuitpython/api_stubs/micropython.py
thonnycontrib/circuitpython/api_stubs/neopixel.py
thonnycontrib/circuitpython/api_stubs/neopixel_write.py
thonnycontrib/circuitpython/api_stubs/nvm.py
thonnycontrib/circuitpython/api_stubs/os.py
thonnycontrib/circuitpython/api_stubs/pulseio.py
thonnycontrib/circuitpython/api_stubs/random.py
thonnycontrib/circuitpython/api_stubs/samd.py
thonnycontrib/circuitpython/api_stubs/storage.py
thonnycontrib/circuitpython/api_stubs/sys.py
thonnycontrib/circuitpython/api_stubs/time.py
thonnycontrib/circuitpython/api_stubs/touchio.py
thonnycontrib/circuitpython/api_stubs/ucollections.py
thonnycontrib/circuitpython/api_stubs/ure.py
thonnycontrib/circuitpython/api_stubs/usb_hid.py
thonnycontrib/circuitpython/api_stubs/ustruct.py
